src/__init__.py
src/manager.py
src/password_generator.py
src/password_manager_error.py
src/utils.py
simplepassword-0.0.0.dist-info/METADATA
simplepassword-0.0.0.dist-info/WHEEL
simplepassword-0.0.0.dist-info/top_level.txt
simplepassword-0.0.0.dist-info/RECORD
